[{"firstName":"Hilliary","lastName":"Kingscote","email":"hkingscote0@google.pl","phoneNo":"2445252928","skypeHandle":"ligula","city":"Rajal Norte","country":"Philippines","timezone":"Asia/Manila"},
{"firstName":"Lydon","lastName":"Lezemere","email":"llezemere1@kickstarter.com","phoneNo":"1249196779","skypeHandle":"consequat","city":"Pāshmūl","country":"Afghanistan","timezone":"Asia/Kabul"},
{"firstName":"Clayborn","lastName":"Yukhov","email":"cyukhov2@youku.com","phoneNo":"6025630777","skypeHandle":"convallis","city":"Yläne","country":"Finland","timezone":"Europe/Helsinki"},
{"firstName":"Marchall","lastName":"Cattemull","email":"mcattemull3@simplemachines.org","phoneNo":"5695410787","skypeHandle":"eget","city":"Shahrak","country":"Afghanistan","timezone":"Asia/Kabul"},
{"firstName":"Burg","lastName":"Celand","email":"bceland4@sitemeter.com","phoneNo":"4189482372","skypeHandle":"quisque","city":"Seria","country":"Brunei","timezone":"Asia/Brunei"},
{"firstName":"Neddie","lastName":"Bossons","email":"nbossons5@pbs.org","phoneNo":"4846403802","skypeHandle":"vel","city":"Altagracia de Orituco","country":"Venezuela","timezone":"America/Caracas"},
{"firstName":"Caddric","lastName":"Castel","email":"ccastel6@spotify.com","phoneNo":"6161057497","skypeHandle":"convallis","city":"Māmu Kānjan","country":"Pakistan","timezone":"Asia/Karachi"},
{"firstName":"Alexio","lastName":"Weatherley","email":"aweatherley7@unicef.org","phoneNo":"7845804494","skypeHandle":"nisi","city":"Zielona Góra","country":"Poland","timezone":"Europe/Warsaw"},
{"firstName":"Kevin","lastName":"Rolles","email":"krolles8@is.gd","phoneNo":"8069440608","skypeHandle":"duis","city":"Qikeshu","country":"China","timezone":"Asia/Harbin"},
{"firstName":"Aldus","lastName":"Hegdonne","email":"ahegdonne9@goo.ne.jp","phoneNo":"2904711601","skypeHandle":"interdum","city":"Dadian","country":"China","timezone":"Asia/Chongqing"},
{"firstName":"Mariette","lastName":"Withringten","email":"mwithringtena@sciencedirect.com","phoneNo":"5122055891","skypeHandle":"primis","city":"Austin","country":"United States","timezone":"America/Chicago"},
{"firstName":"Winslow","lastName":"Pearsey","email":"wpearseyb@army.mil","phoneNo":"5685543356","skypeHandle":"diam","city":"Pajić Polje","country":"Bosnia and Herzegovina","timezone":"Europe/Sarajevo"},
{"firstName":"Ignatius","lastName":"Loweth","email":"ilowethc@blogs.com","phoneNo":"7015434693","skypeHandle":"metus","city":"Nantes","country":"France","timezone":"Europe/Paris"},
{"firstName":"Andrew","lastName":"Hatton","email":"ahattond@amazon.co.jp","phoneNo":"5073828818","skypeHandle":"dapibus","city":"Dmanisi","country":"Georgia","timezone":"Asia/Tbilisi"},
{"firstName":"Sax","lastName":"Feldbrin","email":"sfeldbrine@webeden.co.uk","phoneNo":"3208484166","skypeHandle":"blandit","city":"Kaizuka","country":"Japan","timezone":"Asia/Tokyo"},
{"firstName":"Walsh","lastName":"Stebles","email":"wsteblesf@msu.edu","phoneNo":"3887294785","skypeHandle":"mauris","city":"Otaniemi","country":"Finland","timezone":"Europe/Helsinki"},
{"firstName":"Bibbye","lastName":"Bartosinski","email":"bbartosinskig@pcworld.com","phoneNo":"9934038006","skypeHandle":"ac","city":"Chaoyangdong","country":"China","timezone":"Asia/Chongqing"},
{"firstName":"Sonny","lastName":"Ricciardiello","email":"sricciardielloh@washington.edu","phoneNo":"4423892330","skypeHandle":"augue","city":"Xianhe","country":"China","timezone":"Asia/Chongqing"},
{"firstName":"Roley","lastName":"Asken","email":"raskeni@storify.com","phoneNo":"3326927024","skypeHandle":"interdum","city":"Ketanen","country":"Indonesia","timezone":"Asia/Jakarta"},
{"firstName":"Kettie","lastName":"McCurtain","email":"kmccurtainj@omniture.com","phoneNo":"1915291559","skypeHandle":"placerat","city":"Kapiri Mposhi","country":"Zambia","timezone":"Africa/Lusaka"},
{"firstName":"Forester","lastName":"Airdrie","email":"fairdriek@aboutads.info","phoneNo":"6188920516","skypeHandle":"elit","city":"Mutum","country":"Brazil","timezone":"America/Sao_Paulo"},
{"firstName":"Alley","lastName":"Dunbar","email":"adunbarl@gizmodo.com","phoneNo":"4718586254","skypeHandle":"donec","city":"Longping","country":"China","timezone":"Asia/Chongqing"},
{"firstName":"Thayne","lastName":"Aylmer","email":"taylmerm@chicagotribune.com","phoneNo":"1952023941","skypeHandle":"hac","city":"Río Tercero","country":"Argentina","timezone":"America/Argentina/Cordoba"},
{"firstName":"Ranice","lastName":"Geerits","email":"rgeeritsn@php.net","phoneNo":"3224926558","skypeHandle":"neque","city":"Shcherbinka","country":"Russia","timezone":"Europe/Moscow"},
{"firstName":"Jakie","lastName":"Matskevich","email":"jmatskevicho@java.com","phoneNo":"3831844985","skypeHandle":"sed","city":"Jiaoxiyakou","country":"China","timezone":"Asia/Chongqing"},
{"firstName":"Jeremias","lastName":"Kovacs","email":"jkovacsp@latimes.com","phoneNo":"6565643732","skypeHandle":"nulla","city":"Kosh-Agach","country":"Russia","timezone":"Asia/Ulaanbaatar"},
{"firstName":"Henri","lastName":"Chasle","email":"hchasleq@slashdot.org","phoneNo":"5631369921","skypeHandle":"potenti","city":"Maqia","country":"China","timezone":"Asia/Kashgar"},
{"firstName":"Kathryne","lastName":"Fick","email":"kfickr@phpbb.com","phoneNo":"8504355982","skypeHandle":"morbi","city":"Pensacola","country":"United States","timezone":"America/Chicago"},
{"firstName":"Douglass","lastName":"Pickaver","email":"dpickavers@sun.com","phoneNo":"2976288719","skypeHandle":"ut","city":"Čížkovice","country":"Czech Republic","timezone":"Europe/Prague"},
{"firstName":"Dione","lastName":"Collis","email":"dcollist@blogger.com","phoneNo":"4032666649","skypeHandle":"est","city":"Al Munīrah","country":"Yemen","timezone":"Asia/Aden"},
{"firstName":"Monika","lastName":"Tamburo","email":"mtamburou@usda.gov","phoneNo":"4888032957","skypeHandle":"nulla","city":"Alibago","country":"Philippines","timezone":"Asia/Manila"},
{"firstName":"Lory","lastName":"Vian","email":"lvianv@yolasite.com","phoneNo":"9771541718","skypeHandle":"odio","city":"Cartagena","country":"Colombia","timezone":"America/Bogota"},
{"firstName":"Lulita","lastName":"Giannazzi","email":"lgiannazziw@zimbio.com","phoneNo":"8788412229","skypeHandle":"enim","city":"Nowe Grocholice","country":"Poland","timezone":"Europe/Warsaw"},
{"firstName":"Chevalier","lastName":"Dumphries","email":"cdumphriesx@twitpic.com","phoneNo":"6806732180","skypeHandle":"ipsum","city":"Lappeenranta","country":"Finland","timezone":"Europe/Helsinki"},
{"firstName":"Aidan","lastName":"Cordeix","email":"acordeixy@netvibes.com","phoneNo":"4697781636","skypeHandle":"ipsum","city":"Dallas","country":"United States","timezone":"America/Chicago"},
{"firstName":"Ron","lastName":"Grigolashvill","email":"rgrigolashvillz@examiner.com","phoneNo":"1684775699","skypeHandle":"justo","city":"Cernik","country":"Croatia","timezone":"Europe/Zagreb"},
{"firstName":"Ashley","lastName":"Gyenes","email":"agyenes10@fda.gov","phoneNo":"5831437311","skypeHandle":"potenti","city":"Drammen","country":"Norway","timezone":"Europe/Oslo"},
{"firstName":"Fowler","lastName":"Rubenov","email":"frubenov11@domainmarket.com","phoneNo":"2178499179","skypeHandle":"justo","city":"Islāmkot","country":"Pakistan","timezone":"Asia/Karachi"},
{"firstName":"Cathlene","lastName":"MacKill","email":"cmackill12@time.com","phoneNo":"1672931609","skypeHandle":"tincidunt","city":"Huayucachi","country":"Peru","timezone":"America/Lima"},
{"firstName":"Nickie","lastName":"Webb","email":"nwebb13@gravatar.com","phoneNo":"2884086856","skypeHandle":"dapibus","city":"San Juan Ermita","country":"Guatemala","timezone":"America/Guatemala"}]